{
    "/js/app.js": "/js/app.js",
    "/css/app.css": "/css/app.css",
    "/js/app.b6d16c5708fec4ab7270.hot-update.js": "/js/app.b6d16c5708fec4ab7270.hot-update.js",
    "/js/app.19bce82afb960ffa4c77.hot-update.js": "/js/app.19bce82afb960ffa4c77.hot-update.js",
    "/js/app.343af5bab6b07b5f06f9.hot-update.js": "/js/app.343af5bab6b07b5f06f9.hot-update.js",
    "/js/app.af959c597223df6bd07e.hot-update.js": "/js/app.af959c597223df6bd07e.hot-update.js",
    "/js/app.5fc38aa6159f0f0d8c8e.hot-update.js": "/js/app.5fc38aa6159f0f0d8c8e.hot-update.js",
    "/js/app.714091fa30f04c7945ed.hot-update.js": "/js/app.714091fa30f04c7945ed.hot-update.js",
    "/js/app.485f18e193b1e55e2235.hot-update.js": "/js/app.485f18e193b1e55e2235.hot-update.js",
    "/js/app.f8864292896f7036624d.hot-update.js": "/js/app.f8864292896f7036624d.hot-update.js",
    "/js/app.8530b865076976d10736.hot-update.js": "/js/app.8530b865076976d10736.hot-update.js",
    "/js/app.81f54cc3f0ffda36af55.hot-update.js": "/js/app.81f54cc3f0ffda36af55.hot-update.js",
    "/js/app.47348d5a3a983f7f28de.hot-update.js": "/js/app.47348d5a3a983f7f28de.hot-update.js",
    "/js/app.9fa7e3d1b6c2fe468f1c.hot-update.js": "/js/app.9fa7e3d1b6c2fe468f1c.hot-update.js",
    "/js/app.ce1f7f31436f9b7a2bfb.hot-update.js": "/js/app.ce1f7f31436f9b7a2bfb.hot-update.js",
    "/js/app.f86a8346bd7166e6b3f6.hot-update.js": "/js/app.f86a8346bd7166e6b3f6.hot-update.js",
    "/js/app.b76b2f0e6416da31c24c.hot-update.js": "/js/app.b76b2f0e6416da31c24c.hot-update.js",
    "/js/app.e39ba8280e11ebf35c33.hot-update.js": "/js/app.e39ba8280e11ebf35c33.hot-update.js",
    "/js/app.91582f486a6d2a418dfc.hot-update.js": "/js/app.91582f486a6d2a418dfc.hot-update.js",
    "/js/app.d1f0d0bbe8377c740bd1.hot-update.js": "/js/app.d1f0d0bbe8377c740bd1.hot-update.js",
    "/js/app.b065cafcf5c53f4b2cc0.hot-update.js": "/js/app.b065cafcf5c53f4b2cc0.hot-update.js",
    "/js/app.2531eaa85369cd8bdb84.hot-update.js": "/js/app.2531eaa85369cd8bdb84.hot-update.js",
    "/js/app.4975ded14de6b27e4372.hot-update.js": "/js/app.4975ded14de6b27e4372.hot-update.js",
    "/js/app.3c7b052a11630f4b7e34.hot-update.js": "/js/app.3c7b052a11630f4b7e34.hot-update.js",
    "/js/app.ef9aa8a5213272c2aaf4.hot-update.js": "/js/app.ef9aa8a5213272c2aaf4.hot-update.js",
    "/js/app.8f4ebee7355bc0e34f0f.hot-update.js": "/js/app.8f4ebee7355bc0e34f0f.hot-update.js",
    "/js/app.2323fd5f0bc5f4610bbf.hot-update.js": "/js/app.2323fd5f0bc5f4610bbf.hot-update.js",
    "/js/app.562eaff46e42f3b6b912.hot-update.js": "/js/app.562eaff46e42f3b6b912.hot-update.js",
    "/js/app.19eef55949f366f01de9.hot-update.js": "/js/app.19eef55949f366f01de9.hot-update.js",
    "/js/app.b9c425638f3726be5254.hot-update.js": "/js/app.b9c425638f3726be5254.hot-update.js",
    "/js/app.a7a4179c7c98205a216e.hot-update.js": "/js/app.a7a4179c7c98205a216e.hot-update.js",
    "/js/app.9928905dd4fc62c77673.hot-update.js": "/js/app.9928905dd4fc62c77673.hot-update.js",
    "/js/app.d51d33e978ca4a3c9656.hot-update.js": "/js/app.d51d33e978ca4a3c9656.hot-update.js",
    "/js/app.ca217c6e144aaef099d7.hot-update.js": "/js/app.ca217c6e144aaef099d7.hot-update.js",
    "/js/app.ae1d213235a26c344849.hot-update.js": "/js/app.ae1d213235a26c344849.hot-update.js",
    "/js/app.567acf926e8460067255.hot-update.js": "/js/app.567acf926e8460067255.hot-update.js",
    "/js/app.0100d1656922db5e0339.hot-update.js": "/js/app.0100d1656922db5e0339.hot-update.js",
    "/js/app.536e3fd6cbb4a6743131.hot-update.js": "/js/app.536e3fd6cbb4a6743131.hot-update.js",
    "/js/app.015dbfa7a1d6331f1aeb.hot-update.js": "/js/app.015dbfa7a1d6331f1aeb.hot-update.js",
    "/js/app.f138c2fa70a66b802cf9.hot-update.js": "/js/app.f138c2fa70a66b802cf9.hot-update.js",
    "/js/app.7dbef1aed210e6439ee3.hot-update.js": "/js/app.7dbef1aed210e6439ee3.hot-update.js",
    "/js/app.5f7970fc1b6236dcdf26.hot-update.js": "/js/app.5f7970fc1b6236dcdf26.hot-update.js",
    "/js/app.c7950eb54451b782441c.hot-update.js": "/js/app.c7950eb54451b782441c.hot-update.js",
    "/js/app.03addef24acc9fd0cc83.hot-update.js": "/js/app.03addef24acc9fd0cc83.hot-update.js",
    "/js/app.a1b5a81258195b92deb4.hot-update.js": "/js/app.a1b5a81258195b92deb4.hot-update.js",
    "/js/app.0a3ca5a770793a69fcaa.hot-update.js": "/js/app.0a3ca5a770793a69fcaa.hot-update.js",
    "/js/app.7e6452009a098edcdc85.hot-update.js": "/js/app.7e6452009a098edcdc85.hot-update.js",
    "/js/app.722f6529df175889bc3c.hot-update.js": "/js/app.722f6529df175889bc3c.hot-update.js",
    "/js/app.82ab748aff27648202e3.hot-update.js": "/js/app.82ab748aff27648202e3.hot-update.js",
    "/js/app.72d4ccb25dfdba1ba986.hot-update.js": "/js/app.72d4ccb25dfdba1ba986.hot-update.js",
    "/js/app.97c37ae25dd8e1f99730.hot-update.js": "/js/app.97c37ae25dd8e1f99730.hot-update.js",
    "/js/app.0f974d0db0a4a0529bd9.hot-update.js": "/js/app.0f974d0db0a4a0529bd9.hot-update.js",
    "/js/app.69f773ac31d9852b6cfb.hot-update.js": "/js/app.69f773ac31d9852b6cfb.hot-update.js",
    "/js/app.d0638ec625a28049ae0f.hot-update.js": "/js/app.d0638ec625a28049ae0f.hot-update.js",
    "/js/app.e08ab88f02f5d38f7f7e.hot-update.js": "/js/app.e08ab88f02f5d38f7f7e.hot-update.js",
    "/js/app.9a4035092b60ad5f2312.hot-update.js": "/js/app.9a4035092b60ad5f2312.hot-update.js",
    "/js/app.0c1c834df09f359dd5e0.hot-update.js": "/js/app.0c1c834df09f359dd5e0.hot-update.js",
    "/js/app.044d8c3abe05876c9cb7.hot-update.js": "/js/app.044d8c3abe05876c9cb7.hot-update.js",
    "/js/app.880ee314abe8612293b1.hot-update.js": "/js/app.880ee314abe8612293b1.hot-update.js",
    "/js/app.e6318ad6c6df0b9e53cd.hot-update.js": "/js/app.e6318ad6c6df0b9e53cd.hot-update.js",
    "/js/app.8abd4e41193c57ea4c5b.hot-update.js": "/js/app.8abd4e41193c57ea4c5b.hot-update.js",
    "/js/app.69b0a338cb8da3d88922.hot-update.js": "/js/app.69b0a338cb8da3d88922.hot-update.js",
    "/js/app.ef731af5316785dad37c.hot-update.js": "/js/app.ef731af5316785dad37c.hot-update.js",
    "/js/app.404267ceba4fa6c683ea.hot-update.js": "/js/app.404267ceba4fa6c683ea.hot-update.js",
    "/js/app.d1fa8ddc488a7dffabb7.hot-update.js": "/js/app.d1fa8ddc488a7dffabb7.hot-update.js",
    "/js/app.41a9eacbea01721af1eb.hot-update.js": "/js/app.41a9eacbea01721af1eb.hot-update.js",
    "/js/app.859ea4a184c39307f62f.hot-update.js": "/js/app.859ea4a184c39307f62f.hot-update.js",
    "/js/app.28abed4584504c36bb24.hot-update.js": "/js/app.28abed4584504c36bb24.hot-update.js",
    "/js/app.194692ad92054da4cdd4.hot-update.js": "/js/app.194692ad92054da4cdd4.hot-update.js",
    "/js/app.8211cd931c1a99b88315.hot-update.js": "/js/app.8211cd931c1a99b88315.hot-update.js",
    "/js/app.99f62206b33bb4899a7c.hot-update.js": "/js/app.99f62206b33bb4899a7c.hot-update.js",
    "/js/app.77a5292b5fbe2f7a11ba.hot-update.js": "/js/app.77a5292b5fbe2f7a11ba.hot-update.js",
    "/js/app.f4375d77405bb7dae281.hot-update.js": "/js/app.f4375d77405bb7dae281.hot-update.js",
    "/js/app.a59a993e3f6a733e11a3.hot-update.js": "/js/app.a59a993e3f6a733e11a3.hot-update.js",
    "/js/app.750d4b94a1fb06252124.hot-update.js": "/js/app.750d4b94a1fb06252124.hot-update.js",
    "/js/app.4ef1f599eb0e9ea26f31.hot-update.js": "/js/app.4ef1f599eb0e9ea26f31.hot-update.js",
    "/js/app.264c33023615cf3a1e59.hot-update.js": "/js/app.264c33023615cf3a1e59.hot-update.js",
    "/js/app.2ab5b9e9486238e83800.hot-update.js": "/js/app.2ab5b9e9486238e83800.hot-update.js",
    "/js/app.bc39112bc33fc7af7836.hot-update.js": "/js/app.bc39112bc33fc7af7836.hot-update.js",
    "/js/app.9800569be9cf96147e5f.hot-update.js": "/js/app.9800569be9cf96147e5f.hot-update.js",
    "/js/app.1aa37621480a043673f7.hot-update.js": "/js/app.1aa37621480a043673f7.hot-update.js",
    "/js/app.2bdad5cb3a8d1e6b1712.hot-update.js": "/js/app.2bdad5cb3a8d1e6b1712.hot-update.js",
    "/js/app.14225dc17e4d457138f6.hot-update.js": "/js/app.14225dc17e4d457138f6.hot-update.js",
    "/js/app.8f98bc8fc97516b9302c.hot-update.js": "/js/app.8f98bc8fc97516b9302c.hot-update.js",
    "/js/app.68bf441a26e1e87a10de.hot-update.js": "/js/app.68bf441a26e1e87a10de.hot-update.js",
    "/js/app.ef3cc829aa25a660fa2f.hot-update.js": "/js/app.ef3cc829aa25a660fa2f.hot-update.js",
    "/js/app.2bc12bdef78a98126ca0.hot-update.js": "/js/app.2bc12bdef78a98126ca0.hot-update.js",
    "/js/app.e050bc32a24d4cd3e981.hot-update.js": "/js/app.e050bc32a24d4cd3e981.hot-update.js",
    "/js/app.eb83d8350adb57d3584d.hot-update.js": "/js/app.eb83d8350adb57d3584d.hot-update.js",
    "/js/app.a9538dcb7def34a58b04.hot-update.js": "/js/app.a9538dcb7def34a58b04.hot-update.js",
    "/js/app.bfd166f0857ae10eb581.hot-update.js": "/js/app.bfd166f0857ae10eb581.hot-update.js",
    "/js/app.666644c83f532bafe156.hot-update.js": "/js/app.666644c83f532bafe156.hot-update.js",
    "/js/app.457b7970974d4ff2a764.hot-update.js": "/js/app.457b7970974d4ff2a764.hot-update.js",
    "/js/app.0b96bc7abba9ceccfc46.hot-update.js": "/js/app.0b96bc7abba9ceccfc46.hot-update.js",
    "/js/app.8f1f1a4e3ea5eefbf3a3.hot-update.js": "/js/app.8f1f1a4e3ea5eefbf3a3.hot-update.js",
    "/js/app.b933c6bca930bb5ad1f6.hot-update.js": "/js/app.b933c6bca930bb5ad1f6.hot-update.js",
    "/js/app.c9a733d28df50ecb688e.hot-update.js": "/js/app.c9a733d28df50ecb688e.hot-update.js",
    "/js/app.8ee7d1839d4f194b1af1.hot-update.js": "/js/app.8ee7d1839d4f194b1af1.hot-update.js",
    "/js/app.c336a9d128bad7cfdbbb.hot-update.js": "/js/app.c336a9d128bad7cfdbbb.hot-update.js",
    "/js/app.d64e3e5900e5d26aac2b.hot-update.js": "/js/app.d64e3e5900e5d26aac2b.hot-update.js",
    "/js/app.a4a669e6d8fdbb7bd33c.hot-update.js": "/js/app.a4a669e6d8fdbb7bd33c.hot-update.js",
    "/js/app.0736f2f580b40e73b115.hot-update.js": "/js/app.0736f2f580b40e73b115.hot-update.js",
    "/js/app.ecb1e99d9cffa8080254.hot-update.js": "/js/app.ecb1e99d9cffa8080254.hot-update.js",
    "/js/app.87e589e401c4eacca046.hot-update.js": "/js/app.87e589e401c4eacca046.hot-update.js",
    "/js/app.ef54aec6f4cc30b7ba7c.hot-update.js": "/js/app.ef54aec6f4cc30b7ba7c.hot-update.js",
    "/js/app.d83eb1d9715928cfe016.hot-update.js": "/js/app.d83eb1d9715928cfe016.hot-update.js",
    "/js/app.f7f4f9755d5b7e592ef7.hot-update.js": "/js/app.f7f4f9755d5b7e592ef7.hot-update.js",
    "/js/app.2e6a495f1be72896cfd9.hot-update.js": "/js/app.2e6a495f1be72896cfd9.hot-update.js",
    "/js/app.11bf7c49b08a5961af3b.hot-update.js": "/js/app.11bf7c49b08a5961af3b.hot-update.js",
    "/js/app.04f406a2005a58829e4c.hot-update.js": "/js/app.04f406a2005a58829e4c.hot-update.js",
    "/js/app.3782358ab38060e42ff2.hot-update.js": "/js/app.3782358ab38060e42ff2.hot-update.js",
    "/js/app.adee711a19534d374c12.hot-update.js": "/js/app.adee711a19534d374c12.hot-update.js",
    "/js/app.ade68e8ffabc6c1e5c77.hot-update.js": "/js/app.ade68e8ffabc6c1e5c77.hot-update.js",
    "/js/app.01d9fc82bb0a573cc84e.hot-update.js": "/js/app.01d9fc82bb0a573cc84e.hot-update.js",
    "/js/app.956e37e2ae61c02921a4.hot-update.js": "/js/app.956e37e2ae61c02921a4.hot-update.js",
    "/js/app.23ddece5e07c1b861fd9.hot-update.js": "/js/app.23ddece5e07c1b861fd9.hot-update.js",
    "/js/app.52575b39c23f1a77f7b6.hot-update.js": "/js/app.52575b39c23f1a77f7b6.hot-update.js",
    "/js/app.815374ddc3ae887a2578.hot-update.js": "/js/app.815374ddc3ae887a2578.hot-update.js",
    "/js/app.e27a7f9110f0f56b0381.hot-update.js": "/js/app.e27a7f9110f0f56b0381.hot-update.js",
    "/js/app.956be4f073ae2db0c08c.hot-update.js": "/js/app.956be4f073ae2db0c08c.hot-update.js",
    "/js/app.e61a638d605c6d06f7b4.hot-update.js": "/js/app.e61a638d605c6d06f7b4.hot-update.js",
    "/js/app.c674e6add0e3a4763028.hot-update.js": "/js/app.c674e6add0e3a4763028.hot-update.js",
    "/js/app.65b8d34511c95d1365c7.hot-update.js": "/js/app.65b8d34511c95d1365c7.hot-update.js",
    "/js/app.dba93c544652ade3a2ed.hot-update.js": "/js/app.dba93c544652ade3a2ed.hot-update.js",
    "/js/app.27161cd24816670665f8.hot-update.js": "/js/app.27161cd24816670665f8.hot-update.js",
    "/js/app.8d85a9e4605b8724c03c.hot-update.js": "/js/app.8d85a9e4605b8724c03c.hot-update.js",
    "/js/app.96818d3c9a67393e293a.hot-update.js": "/js/app.96818d3c9a67393e293a.hot-update.js",
    "/js/app.6cd666d87556004a4c5d.hot-update.js": "/js/app.6cd666d87556004a4c5d.hot-update.js",
    "/js/app.96e37a2e980aa2ba101f.hot-update.js": "/js/app.96e37a2e980aa2ba101f.hot-update.js",
    "/js/app.5e7d44c1a50e0b3b4b03.hot-update.js": "/js/app.5e7d44c1a50e0b3b4b03.hot-update.js",
    "/js/app.10b187fbe1467ed237ba.hot-update.js": "/js/app.10b187fbe1467ed237ba.hot-update.js",
    "/js/app.1e8f881a8e9a60709593.hot-update.js": "/js/app.1e8f881a8e9a60709593.hot-update.js",
    "/js/app.57929cda79b9ee63cfbd.hot-update.js": "/js/app.57929cda79b9ee63cfbd.hot-update.js",
    "/js/app.b18780ed94a71d08651f.hot-update.js": "/js/app.b18780ed94a71d08651f.hot-update.js",
    "/js/app.d29ee643967bf38ad15e.hot-update.js": "/js/app.d29ee643967bf38ad15e.hot-update.js",
    "/js/app.f3b6119aa020e1bb3e3a.hot-update.js": "/js/app.f3b6119aa020e1bb3e3a.hot-update.js",
    "/js/app.bfe6df85cb7822149b9f.hot-update.js": "/js/app.bfe6df85cb7822149b9f.hot-update.js",
    "/js/app.1ca565bd3f9105a4cc39.hot-update.js": "/js/app.1ca565bd3f9105a4cc39.hot-update.js",
    "/js/app.5486996b606efbb3221b.hot-update.js": "/js/app.5486996b606efbb3221b.hot-update.js",
    "/js/app.b6a3d52b7ee4b339c01e.hot-update.js": "/js/app.b6a3d52b7ee4b339c01e.hot-update.js",
    "/js/app.710ad09662c9357f962a.hot-update.js": "/js/app.710ad09662c9357f962a.hot-update.js",
    "/js/app.835254698545c2ce4f75.hot-update.js": "/js/app.835254698545c2ce4f75.hot-update.js",
    "/js/app.10313fb31d839b898366.hot-update.js": "/js/app.10313fb31d839b898366.hot-update.js",
    "/js/app.0d6a02d7be455064ccd1.hot-update.js": "/js/app.0d6a02d7be455064ccd1.hot-update.js",
    "/js/app.3666ad11a61cf2210952.hot-update.js": "/js/app.3666ad11a61cf2210952.hot-update.js",
    "/js/app.d86ec1937261b918cfa8.hot-update.js": "/js/app.d86ec1937261b918cfa8.hot-update.js",
    "/js/app.33d5e8e09433282c0a87.hot-update.js": "/js/app.33d5e8e09433282c0a87.hot-update.js",
    "/js/app.05c800c9368638f8439a.hot-update.js": "/js/app.05c800c9368638f8439a.hot-update.js",
    "/js/app.234b169c8a6e6fc905ec.hot-update.js": "/js/app.234b169c8a6e6fc905ec.hot-update.js",
    "/js/app.bdb3d7470acae37a02db.hot-update.js": "/js/app.bdb3d7470acae37a02db.hot-update.js",
    "/js/app.ab7e660fcfae029caa28.hot-update.js": "/js/app.ab7e660fcfae029caa28.hot-update.js",
    "/js/app.60f3a697668b8ed48d41.hot-update.js": "/js/app.60f3a697668b8ed48d41.hot-update.js",
    "/js/app.0487fac5221c140019c3.hot-update.js": "/js/app.0487fac5221c140019c3.hot-update.js",
    "/js/app.e39087dd38530377c709.hot-update.js": "/js/app.e39087dd38530377c709.hot-update.js",
    "/js/app.2ab26282e91ac5eaaae7.hot-update.js": "/js/app.2ab26282e91ac5eaaae7.hot-update.js",
    "/js/app.b219fd96e27f024d4efe.hot-update.js": "/js/app.b219fd96e27f024d4efe.hot-update.js",
    "/js/app.64afe6bb0c81aa3f19fa.hot-update.js": "/js/app.64afe6bb0c81aa3f19fa.hot-update.js",
    "/js/app.510a8c737bb8f43c6674.hot-update.js": "/js/app.510a8c737bb8f43c6674.hot-update.js",
    "/js/app.239fecbcc86ebabcaaca.hot-update.js": "/js/app.239fecbcc86ebabcaaca.hot-update.js",
    "/js/app.faaaf302f24d31044a60.hot-update.js": "/js/app.faaaf302f24d31044a60.hot-update.js",
    "/js/app.77107e3d234865833ad8.hot-update.js": "/js/app.77107e3d234865833ad8.hot-update.js",
    "/js/app.c7bfcf01316d8e4d97d8.hot-update.js": "/js/app.c7bfcf01316d8e4d97d8.hot-update.js",
    "/js/app.3581301b1d4cba32081d.hot-update.js": "/js/app.3581301b1d4cba32081d.hot-update.js",
    "/js/app.c13a1a96e1e8f57bc6bd.hot-update.js": "/js/app.c13a1a96e1e8f57bc6bd.hot-update.js",
    "/js/app.8d55efd3a7c07b58dc42.hot-update.js": "/js/app.8d55efd3a7c07b58dc42.hot-update.js",
    "/js/app.f89b319fa0b2671f04ed.hot-update.js": "/js/app.f89b319fa0b2671f04ed.hot-update.js",
    "/js/app.7b93e0773d5832932e05.hot-update.js": "/js/app.7b93e0773d5832932e05.hot-update.js",
    "/js/app.3f62a79b5b496a9eb331.hot-update.js": "/js/app.3f62a79b5b496a9eb331.hot-update.js",
    "/js/app.5c6d50daa8b4018a61a9.hot-update.js": "/js/app.5c6d50daa8b4018a61a9.hot-update.js",
    "/js/app.c90048e8c0455605d775.hot-update.js": "/js/app.c90048e8c0455605d775.hot-update.js",
    "/js/app.531e253d1e8ee0643608.hot-update.js": "/js/app.531e253d1e8ee0643608.hot-update.js",
    "/js/app.35ac8864106f8be132e0.hot-update.js": "/js/app.35ac8864106f8be132e0.hot-update.js",
    "/js/app.cb0d92c0c105d5eae875.hot-update.js": "/js/app.cb0d92c0c105d5eae875.hot-update.js",
    "/js/app.7ae8bf6e2b86e10fabad.hot-update.js": "/js/app.7ae8bf6e2b86e10fabad.hot-update.js",
    "/js/app.02575607ddb8fd973ecb.hot-update.js": "/js/app.02575607ddb8fd973ecb.hot-update.js",
    "/js/app.135ffbfae8b9630ee53b.hot-update.js": "/js/app.135ffbfae8b9630ee53b.hot-update.js",
    "/js/app.21e498e7512e99d87f78.hot-update.js": "/js/app.21e498e7512e99d87f78.hot-update.js",
    "/js/app.0384cc01c701db8b5f47.hot-update.js": "/js/app.0384cc01c701db8b5f47.hot-update.js",
    "/js/app.8c8b547326dab087201e.hot-update.js": "/js/app.8c8b547326dab087201e.hot-update.js",
    "/js/app.d29755bc4f996a3a47aa.hot-update.js": "/js/app.d29755bc4f996a3a47aa.hot-update.js",
    "/js/app.b92e8a38c943087bf658.hot-update.js": "/js/app.b92e8a38c943087bf658.hot-update.js",
    "/js/app.bd46576172b86b572cfa.hot-update.js": "/js/app.bd46576172b86b572cfa.hot-update.js",
    "/js/app.e37e93738763d6ee431e.hot-update.js": "/js/app.e37e93738763d6ee431e.hot-update.js",
    "/js/app.533037c69ae2f120e569.hot-update.js": "/js/app.533037c69ae2f120e569.hot-update.js",
    "/js/app.64fe807563f16b1ba489.hot-update.js": "/js/app.64fe807563f16b1ba489.hot-update.js",
    "/js/app.9e37c0821bddc8f18a92.hot-update.js": "/js/app.9e37c0821bddc8f18a92.hot-update.js",
    "/js/app.a93eac34a50567b37412.hot-update.js": "/js/app.a93eac34a50567b37412.hot-update.js",
    "/js/app.4349f25bbd92bfd5a7aa.hot-update.js": "/js/app.4349f25bbd92bfd5a7aa.hot-update.js",
    "/js/app.e8c7ea8209e11425c3a6.hot-update.js": "/js/app.e8c7ea8209e11425c3a6.hot-update.js",
    "/js/app.78784e638dcad32f365d.hot-update.js": "/js/app.78784e638dcad32f365d.hot-update.js",
    "/js/app.431bd5efc4f328419192.hot-update.js": "/js/app.431bd5efc4f328419192.hot-update.js",
    "/js/app.8cbf5e2363a1564eaece.hot-update.js": "/js/app.8cbf5e2363a1564eaece.hot-update.js",
    "/js/app.2664d83845d59b60bdf2.hot-update.js": "/js/app.2664d83845d59b60bdf2.hot-update.js",
    "/js/app.fb537087d10bfca9d5fd.hot-update.js": "/js/app.fb537087d10bfca9d5fd.hot-update.js",
    "/js/app.c90f81a7ab85a4fde97e.hot-update.js": "/js/app.c90f81a7ab85a4fde97e.hot-update.js",
    "/js/app.282c5853dd0d9fc19404.hot-update.js": "/js/app.282c5853dd0d9fc19404.hot-update.js",
    "/js/app.7f11d43ec08ee6891b21.hot-update.js": "/js/app.7f11d43ec08ee6891b21.hot-update.js",
    "/js/app.818ea7c72a26056c10ac.hot-update.js": "/js/app.818ea7c72a26056c10ac.hot-update.js",
    "/js/app.265ccfda5e91416e450c.hot-update.js": "/js/app.265ccfda5e91416e450c.hot-update.js",
    "/js/app.7590f7d2dce48db38d86.hot-update.js": "/js/app.7590f7d2dce48db38d86.hot-update.js",
    "/js/app.62bd73c9da3bd6847073.hot-update.js": "/js/app.62bd73c9da3bd6847073.hot-update.js",
    "/js/app.a9a68ecaf9bb2962986b.hot-update.js": "/js/app.a9a68ecaf9bb2962986b.hot-update.js",
    "/js/app.9094cf1aeacbddac74b2.hot-update.js": "/js/app.9094cf1aeacbddac74b2.hot-update.js",
    "/js/app.967b17cc61662191bc95.hot-update.js": "/js/app.967b17cc61662191bc95.hot-update.js",
    "/js/app.96fe3b7f37013981d5b3.hot-update.js": "/js/app.96fe3b7f37013981d5b3.hot-update.js",
    "/js/app.eee44242a6aec9f1d608.hot-update.js": "/js/app.eee44242a6aec9f1d608.hot-update.js",
    "/js/app.b9ce91f30641feebe498.hot-update.js": "/js/app.b9ce91f30641feebe498.hot-update.js",
    "/js/app.baee2fbd54a87195eea7.hot-update.js": "/js/app.baee2fbd54a87195eea7.hot-update.js",
    "/js/app.83a93741f6a528fd7997.hot-update.js": "/js/app.83a93741f6a528fd7997.hot-update.js",
    "/js/app.c5f6e4aaae753bdbe889.hot-update.js": "/js/app.c5f6e4aaae753bdbe889.hot-update.js",
    "/js/app.cb4af30f65e95f47ecab.hot-update.js": "/js/app.cb4af30f65e95f47ecab.hot-update.js",
    "/js/app.81b60cc86d2da4887a5b.hot-update.js": "/js/app.81b60cc86d2da4887a5b.hot-update.js",
    "/js/app.857e2fd031d29918fb20.hot-update.js": "/js/app.857e2fd031d29918fb20.hot-update.js",
    "/js/app.b69369d82658da08b832.hot-update.js": "/js/app.b69369d82658da08b832.hot-update.js",
    "/js/app.54ff081a1f6de448ed4f.hot-update.js": "/js/app.54ff081a1f6de448ed4f.hot-update.js",
    "/js/app.1a280791ac8139a609b0.hot-update.js": "/js/app.1a280791ac8139a609b0.hot-update.js",
    "/js/app.b944f40af324626b373b.hot-update.js": "/js/app.b944f40af324626b373b.hot-update.js",
    "/js/app.4f3572806c9c61e59a04.hot-update.js": "/js/app.4f3572806c9c61e59a04.hot-update.js",
    "/js/app.dbaf732dfdf434b1271e.hot-update.js": "/js/app.dbaf732dfdf434b1271e.hot-update.js",
    "/js/app.954bf3a2fd4542a404e5.hot-update.js": "/js/app.954bf3a2fd4542a404e5.hot-update.js",
    "/js/app.727c7f2f6523e81af251.hot-update.js": "/js/app.727c7f2f6523e81af251.hot-update.js",
    "/js/app.cce3246c1075f6b5fbcf.hot-update.js": "/js/app.cce3246c1075f6b5fbcf.hot-update.js",
    "/js/app.3d59ef9ba5722e0c835d.hot-update.js": "/js/app.3d59ef9ba5722e0c835d.hot-update.js",
    "/js/app.47405b2010cb7f610901.hot-update.js": "/js/app.47405b2010cb7f610901.hot-update.js",
    "/js/app.64509c28903ba1481c16.hot-update.js": "/js/app.64509c28903ba1481c16.hot-update.js",
    "/js/app.46842fa5c0441ac9a10d.hot-update.js": "/js/app.46842fa5c0441ac9a10d.hot-update.js",
    "/js/app.3662a756a9fc8a1a518d.hot-update.js": "/js/app.3662a756a9fc8a1a518d.hot-update.js",
    "/js/app.1c6fbf8c269c91445a12.hot-update.js": "/js/app.1c6fbf8c269c91445a12.hot-update.js",
    "/js/app.54010051414651c1ff35.hot-update.js": "/js/app.54010051414651c1ff35.hot-update.js",
    "/js/app.4e1b4714469b907f4d56.hot-update.js": "/js/app.4e1b4714469b907f4d56.hot-update.js",
    "/js/app.d0c2f0223db4910e20c1.hot-update.js": "/js/app.d0c2f0223db4910e20c1.hot-update.js",
    "/js/app.980b5db2243ec5e7f3ef.hot-update.js": "/js/app.980b5db2243ec5e7f3ef.hot-update.js",
    "/js/app.f74bf00ba22cd609a7b1.hot-update.js": "/js/app.f74bf00ba22cd609a7b1.hot-update.js",
    "/js/app.afc995a008fd51910615.hot-update.js": "/js/app.afc995a008fd51910615.hot-update.js",
    "/js/app.7d89279dab3e9dd362f1.hot-update.js": "/js/app.7d89279dab3e9dd362f1.hot-update.js",
    "/js/app.74e4911558e98e534f18.hot-update.js": "/js/app.74e4911558e98e534f18.hot-update.js",
    "/js/app.04d0cae54ef0e9c6b74a.hot-update.js": "/js/app.04d0cae54ef0e9c6b74a.hot-update.js",
    "/js/app.3c5ff96fdad8da3b978a.hot-update.js": "/js/app.3c5ff96fdad8da3b978a.hot-update.js",
    "/js/app.802734b50cf3cc8b18dd.hot-update.js": "/js/app.802734b50cf3cc8b18dd.hot-update.js",
    "/js/app.f03a4fc120d27feabd08.hot-update.js": "/js/app.f03a4fc120d27feabd08.hot-update.js",
    "/js/app.de826e325470bcc56476.hot-update.js": "/js/app.de826e325470bcc56476.hot-update.js",
    "/js/app.5d0654859fef5cdf27c6.hot-update.js": "/js/app.5d0654859fef5cdf27c6.hot-update.js",
    "/js/app.9e5614787a184be46f85.hot-update.js": "/js/app.9e5614787a184be46f85.hot-update.js",
    "/js/app.b4f23331214bab3a45d4.hot-update.js": "/js/app.b4f23331214bab3a45d4.hot-update.js",
    "/js/app.7f0ca9d8beda8f69bcd1.hot-update.js": "/js/app.7f0ca9d8beda8f69bcd1.hot-update.js",
    "/js/app.b8f6234f5e450c42052e.hot-update.js": "/js/app.b8f6234f5e450c42052e.hot-update.js",
    "/js/app.b8852443456f6693a9ba.hot-update.js": "/js/app.b8852443456f6693a9ba.hot-update.js",
    "/js/app.d0e1c6746017ad73e900.hot-update.js": "/js/app.d0e1c6746017ad73e900.hot-update.js",
    "/js/app.00b3cac34cde96a7b64d.hot-update.js": "/js/app.00b3cac34cde96a7b64d.hot-update.js",
    "/js/app.4c90da89bed267ac5988.hot-update.js": "/js/app.4c90da89bed267ac5988.hot-update.js",
    "/js/app.0695760c29acffc200a0.hot-update.js": "/js/app.0695760c29acffc200a0.hot-update.js",
    "/js/app.52fb2f977bd0c9bb7430.hot-update.js": "/js/app.52fb2f977bd0c9bb7430.hot-update.js",
    "/js/app.f157e9ba295e414691e7.hot-update.js": "/js/app.f157e9ba295e414691e7.hot-update.js",
    "/js/app.e9ce299d1886a975581f.hot-update.js": "/js/app.e9ce299d1886a975581f.hot-update.js",
    "/js/app.67fb40e3ea586148213b.hot-update.js": "/js/app.67fb40e3ea586148213b.hot-update.js",
    "/js/app.dfcc88f9ab448e66464e.hot-update.js": "/js/app.dfcc88f9ab448e66464e.hot-update.js",
    "/js/app.0e546b0e99d025b3756a.hot-update.js": "/js/app.0e546b0e99d025b3756a.hot-update.js",
    "/js/app.024d25007fd691aab00a.hot-update.js": "/js/app.024d25007fd691aab00a.hot-update.js",
    "/js/app.d62b9cb0ab4c755ae82b.hot-update.js": "/js/app.d62b9cb0ab4c755ae82b.hot-update.js",
    "/js/app.7bc0f659e9eb2806b71a.hot-update.js": "/js/app.7bc0f659e9eb2806b71a.hot-update.js",
    "/js/app.d5427a7b0623cf6a9903.hot-update.js": "/js/app.d5427a7b0623cf6a9903.hot-update.js",
    "/js/app.9ae113ce6e4f23416134.hot-update.js": "/js/app.9ae113ce6e4f23416134.hot-update.js",
    "/js/app.c76f44c04274a77e77dc.hot-update.js": "/js/app.c76f44c04274a77e77dc.hot-update.js",
    "/js/app.ca4a3c1fee00fb129f5a.hot-update.js": "/js/app.ca4a3c1fee00fb129f5a.hot-update.js",
    "/js/app.2325734fc2f35ed3b3c3.hot-update.js": "/js/app.2325734fc2f35ed3b3c3.hot-update.js",
    "/js/app.b2c63b99e7283552d741.hot-update.js": "/js/app.b2c63b99e7283552d741.hot-update.js",
    "/js/app.74ec3fce7563cd2f9440.hot-update.js": "/js/app.74ec3fce7563cd2f9440.hot-update.js",
    "/js/app.61809149d81db7afa8d9.hot-update.js": "/js/app.61809149d81db7afa8d9.hot-update.js",
    "/js/app.8ed83511e01a74ad4d62.hot-update.js": "/js/app.8ed83511e01a74ad4d62.hot-update.js",
    "/js/app.267b376865a99fbeec09.hot-update.js": "/js/app.267b376865a99fbeec09.hot-update.js",
    "/js/app.ee31b3bd6fd7694449ca.hot-update.js": "/js/app.ee31b3bd6fd7694449ca.hot-update.js",
    "/js/app.b7598b9d9f664efaf42e.hot-update.js": "/js/app.b7598b9d9f664efaf42e.hot-update.js",
    "/js/app.c7b8249f566ae4a9219c.hot-update.js": "/js/app.c7b8249f566ae4a9219c.hot-update.js",
    "/js/app.5153f795d9c52398bbd4.hot-update.js": "/js/app.5153f795d9c52398bbd4.hot-update.js",
    "/js/app.513cf572ba30bccddb77.hot-update.js": "/js/app.513cf572ba30bccddb77.hot-update.js",
    "/js/app.fc579a95e4bcced3ef16.hot-update.js": "/js/app.fc579a95e4bcced3ef16.hot-update.js",
    "/js/app.996d763d2a52b7b32da7.hot-update.js": "/js/app.996d763d2a52b7b32da7.hot-update.js",
    "/js/app.5fca3be5ba9ea44634a1.hot-update.js": "/js/app.5fca3be5ba9ea44634a1.hot-update.js",
    "/js/app.581d270070f428a46c1b.hot-update.js": "/js/app.581d270070f428a46c1b.hot-update.js",
    "/js/app.dad666b4bb44efcab259.hot-update.js": "/js/app.dad666b4bb44efcab259.hot-update.js",
    "/js/app.860bb39ff8b7bb3dcf02.hot-update.js": "/js/app.860bb39ff8b7bb3dcf02.hot-update.js",
    "/js/app.a6dc1d9a85861516786c.hot-update.js": "/js/app.a6dc1d9a85861516786c.hot-update.js",
    "/js/app.6e66a5b74d6fbdd209d5.hot-update.js": "/js/app.6e66a5b74d6fbdd209d5.hot-update.js",
    "/js/app.f874ac2f00811c7ac016.hot-update.js": "/js/app.f874ac2f00811c7ac016.hot-update.js",
    "/js/app.3de10e97179c22989aa8.hot-update.js": "/js/app.3de10e97179c22989aa8.hot-update.js",
    "/js/app.aa1bc025ea8a0aba0ea1.hot-update.js": "/js/app.aa1bc025ea8a0aba0ea1.hot-update.js",
    "/js/app.173bc88acef9bdad665b.hot-update.js": "/js/app.173bc88acef9bdad665b.hot-update.js",
    "/js/app.eac6cce3a9d03636308c.hot-update.js": "/js/app.eac6cce3a9d03636308c.hot-update.js",
    "/js/app.443d16f8dd7ad526bd73.hot-update.js": "/js/app.443d16f8dd7ad526bd73.hot-update.js",
    "/js/app.bdc7fd21358cceeaf5a5.hot-update.js": "/js/app.bdc7fd21358cceeaf5a5.hot-update.js",
    "/js/app.75cb9e379327295e8f03.hot-update.js": "/js/app.75cb9e379327295e8f03.hot-update.js",
    "/js/app.0fbe49d04ddda6f79e7d.hot-update.js": "/js/app.0fbe49d04ddda6f79e7d.hot-update.js",
    "/js/app.17aa50d0e2977f8f6a85.hot-update.js": "/js/app.17aa50d0e2977f8f6a85.hot-update.js",
    "/js/app.a695c77296c58ab2a8ff.hot-update.js": "/js/app.a695c77296c58ab2a8ff.hot-update.js",
    "/js/app.fdbe86c82a55c7d27ff1.hot-update.js": "/js/app.fdbe86c82a55c7d27ff1.hot-update.js",
    "/js/app.0964ebc198090c59c348.hot-update.js": "/js/app.0964ebc198090c59c348.hot-update.js",
    "/js/app.8484c4553785977b83bc.hot-update.js": "/js/app.8484c4553785977b83bc.hot-update.js",
    "/js/app.b809d3b8fbb23e804fea.hot-update.js": "/js/app.b809d3b8fbb23e804fea.hot-update.js",
    "/js/app.498e5915598b01722510.hot-update.js": "/js/app.498e5915598b01722510.hot-update.js",
    "/js/app.c4865abd04538b523e10.hot-update.js": "/js/app.c4865abd04538b523e10.hot-update.js",
    "/js/app.d330534dba3df515047d.hot-update.js": "/js/app.d330534dba3df515047d.hot-update.js",
    "/js/app.0142fb29ea4ec06edee9.hot-update.js": "/js/app.0142fb29ea4ec06edee9.hot-update.js",
    "/js/app.cf412a5c310ccf12fc89.hot-update.js": "/js/app.cf412a5c310ccf12fc89.hot-update.js",
    "/js/app.7fb445c92a0990d18e7e.hot-update.js": "/js/app.7fb445c92a0990d18e7e.hot-update.js",
    "/js/app.7ae60d6f6bc65b130d43.hot-update.js": "/js/app.7ae60d6f6bc65b130d43.hot-update.js",
    "/js/app.870de377fed522ef97c9.hot-update.js": "/js/app.870de377fed522ef97c9.hot-update.js",
    "/js/app.810e8843ead0d92d4e48.hot-update.js": "/js/app.810e8843ead0d92d4e48.hot-update.js",
    "/js/app.b89722539fc07665e4c3.hot-update.js": "/js/app.b89722539fc07665e4c3.hot-update.js",
    "/js/app.425bc5a5ec6fe9716a5a.hot-update.js": "/js/app.425bc5a5ec6fe9716a5a.hot-update.js",
    "/js/app.903e2fc201ea9e1580af.hot-update.js": "/js/app.903e2fc201ea9e1580af.hot-update.js",
    "/js/app.6b52fdb88e41b1874d15.hot-update.js": "/js/app.6b52fdb88e41b1874d15.hot-update.js"
}
